dirspec/__init__.py
dirspec/basedir.py
dirspec/utils.py
dirspec/tests/__init__.py
dirspec/tests/test_basedir.py
dirspec/tests/test_utils.py
geofrontcli/__init__.py
geofrontcli/cli.py
geofrontcli/client.py
geofrontcli/key.py
geofrontcli/ssl.py
geofrontcli/version.py
geofront_cli-0.4.4.dist-info/LICENSE
geofront_cli-0.4.4.dist-info/METADATA
geofront_cli-0.4.4.dist-info/WHEEL
geofront_cli-0.4.4.dist-info/entry_points.txt
geofront_cli-0.4.4.dist-info/top_level.txt
geofront_cli-0.4.4.dist-info/RECORD
