Metadata-Version: 2.1
Name: geofront-cli
Version: 0.4.4
Summary: CLI client for Geofront, a simple SSH key management server
Home-page: https://github.com/spoqa/geofront-cli
Author: Hong Minhee
Author-email: hongminhee@member.fsf.org
Maintainer: Spoqa
Maintainer-email: dev@spoqa.com
License: GPLv3 or later
Platform: UNKNOWN
Classifier: Development Status :: 4 - Beta
Classifier: Environment :: Console
Classifier: Intended Audience :: Developers
Classifier: Intended Audience :: System Administrators
Classifier: License :: OSI Approved :: GNU General Public License v3 or later (GPLv3+)
Classifier: Operating System :: POSIX
Classifier: Programming Language :: Python :: 2
Classifier: Programming Language :: Python :: 2.7
Classifier: Programming Language :: Python :: 3
Classifier: Programming Language :: Python :: 3.3
Classifier: Programming Language :: Python :: 3.4
Classifier: Programming Language :: Python :: 3.5
Classifier: Programming Language :: Python :: 3.6
Classifier: Programming Language :: Python :: Implementation :: CPython
Classifier: Programming Language :: Python :: Implementation :: PyPy
Classifier: Topic :: System :: Systems Administration :: Authentication/Directory
Classifier: Topic :: Utilities
Requires-Dist: keyring (>=3.7)
Requires-Dist: logging-spinner (>=0.2.1)
Requires-Dist: certifi
Requires-Dist: six
Requires-Dist: iterfzf (<1.0.0.0.0,>=0.2.0.16.7)
Requires-Dist: enum34 ; python_version<'3.4'
Requires-Dist: pypiwin32 ; sys_platform=='win32'
